snipster/__init__.py
snipster/__main__.py
snipster/cli.py
snipster/exceptions.py
snipster/models.py
snipster/repo.py
snipster/snipster.db
snipster/util.py
snipster_bli-0.1.0.dist-info/METADATA
snipster_bli-0.1.0.dist-info/WHEEL
snipster_bli-0.1.0.dist-info/entry_points.txt
snipster_bli-0.1.0.dist-info/RECORD
