Metadata-Version: 2.4
Name: snipster-bli
Version: 0.1.0
Summary: A code snippet management tool
Author-email: bli <benli133@gmail.com>
Requires-Python: >=3.13
Requires-Dist: alembic>=1.16.2
Requires-Dist: fastapi[all]>=0.116.1
Requires-Dist: httpx>=0.28.1
Requires-Dist: nicegui>=2.21.1
Requires-Dist: psycopg2-binary>=2.9.10
Requires-Dist: python-decouple>=3.8
Requires-Dist: rapidfuzz>=3.13.0
Requires-Dist: sqlmodel>=0.0.24
Requires-Dist: typer>=0.16.0
